{
"meta":{"test_sets":[],"test_metrics":[],"learn_metrics":[{"best_value":"Min","name":"Logloss"}],"launch_mode":"Train","parameters":"","iteration_count":100,"learn_sets":["learn"],"name":"experiment"},
"iterations":[
{"learn":[0.6243673842],"iteration":0,"passed_time":0.07476746594,"remaining_time":7.401979128},
{"learn":[0.5805747959],"iteration":1,"passed_time":0.1448099547,"remaining_time":7.095687781},
{"learn":[0.5513952827],"iteration":2,"passed_time":0.2262452922,"remaining_time":7.315264449},
{"learn":[0.5263313484],"iteration":3,"passed_time":0.3098685316,"remaining_time":7.436844759},
{"learn":[0.5069579097],"iteration":4,"passed_time":0.3817995443,"remaining_time":7.254191341},
{"learn":[0.4899159649],"iteration":5,"passed_time":0.4388878442,"remaining_time":6.87590956},
{"learn":[0.4738214656],"iteration":6,"passed_time":0.5060701625,"remaining_time":6.723503587},
{"learn":[0.4611171068],"iteration":7,"passed_time":0.5673926324,"remaining_time":6.525015272},
{"learn":[0.4499259131],"iteration":8,"passed_time":0.6409035106,"remaining_time":6.480246607},
{"learn":[0.4398905836],"iteration":9,"passed_time":0.709529829,"remaining_time":6.385768461},
{"learn":[0.4314585086],"iteration":10,"passed_time":0.782576556,"remaining_time":6.331755771},
{"learn":[0.4247231647],"iteration":11,"passed_time":0.8519744805,"remaining_time":6.247812857},
{"learn":[0.4182411793],"iteration":12,"passed_time":0.924709646,"remaining_time":6.188441477},
{"learn":[0.4109347643],"iteration":13,"passed_time":0.9957899419,"remaining_time":6.116995357},
{"learn":[0.4047687803],"iteration":14,"passed_time":1.069233866,"remaining_time":6.05899191},
{"learn":[0.3980777795],"iteration":15,"passed_time":1.165751395,"remaining_time":6.120194822},
{"learn":[0.3920683915],"iteration":16,"passed_time":1.245872214,"remaining_time":6.082787868},
{"learn":[0.3862457248],"iteration":17,"passed_time":1.305217604,"remaining_time":5.945991305},
{"learn":[0.3809298733],"iteration":18,"passed_time":1.36969884,"remaining_time":5.839242421},
{"learn":[0.3767741816],"iteration":19,"passed_time":1.430837906,"remaining_time":5.723351625},
{"learn":[0.3722880105],"iteration":20,"passed_time":1.488432607,"remaining_time":5.599341714},
{"learn":[0.3666741358],"iteration":21,"passed_time":1.558062341,"remaining_time":5.524039208},
{"learn":[0.3610779231],"iteration":22,"passed_time":1.617565184,"remaining_time":5.415326919},
{"learn":[0.3572354875],"iteration":23,"passed_time":1.684251495,"remaining_time":5.333463069},
{"learn":[0.3544812039],"iteration":24,"passed_time":1.755485796,"remaining_time":5.266457388},
{"learn":[0.3515922478],"iteration":25,"passed_time":1.824782864,"remaining_time":5.193612767},
{"learn":[0.3471402168],"iteration":26,"passed_time":1.88583986,"remaining_time":5.098752213},
{"learn":[0.3417177473],"iteration":27,"passed_time":1.953140262,"remaining_time":5.022360673},
{"learn":[0.338503497],"iteration":28,"passed_time":2.027988706,"remaining_time":4.965075796},
{"learn":[0.334955195],"iteration":29,"passed_time":2.112020683,"remaining_time":4.92804826},
{"learn":[0.3319806549],"iteration":30,"passed_time":2.184484023,"remaining_time":4.862238633},
{"learn":[0.3288676766],"iteration":31,"passed_time":2.257912293,"remaining_time":4.798063623},
{"learn":[0.3259415122],"iteration":32,"passed_time":2.339417668,"remaining_time":4.74972678},
{"learn":[0.322937915],"iteration":33,"passed_time":2.409208168,"remaining_time":4.676698208},
{"learn":[0.3199657508],"iteration":34,"passed_time":2.481737436,"remaining_time":4.608940953},
{"learn":[0.3169174971],"iteration":35,"passed_time":2.552411497,"remaining_time":4.537620439},
{"learn":[0.3139001615],"iteration":36,"passed_time":2.624116673,"remaining_time":4.468090551},
{"learn":[0.3106965555],"iteration":37,"passed_time":2.702573736,"remaining_time":4.409462412},
{"learn":[0.3073532663],"iteration":38,"passed_time":2.772467272,"remaining_time":4.336423169},
{"learn":[0.3047980881],"iteration":39,"passed_time":2.843309997,"remaining_time":4.264964995},
{"learn":[0.3018231569],"iteration":40,"passed_time":2.918296812,"remaining_time":4.199500291},
{"learn":[0.298656514],"iteration":41,"passed_time":3.008084751,"remaining_time":4.1540218},
{"learn":[0.296194443],"iteration":42,"passed_time":3.079111862,"remaining_time":4.081613398},
{"learn":[0.2933753177],"iteration":43,"passed_time":3.14973691,"remaining_time":4.008756067},
{"learn":[0.2908776351],"iteration":44,"passed_time":3.22296564,"remaining_time":3.939180227},
{"learn":[0.2881895896],"iteration":45,"passed_time":3.29565574,"remaining_time":3.86881326},
{"learn":[0.2856921414],"iteration":46,"passed_time":3.365970503,"remaining_time":3.795668865},
{"learn":[0.2835079234],"iteration":47,"passed_time":3.437104662,"remaining_time":3.72353005},
{"learn":[0.2810444587],"iteration":48,"passed_time":3.513231477,"remaining_time":3.65662868},
{"learn":[0.2787489973],"iteration":49,"passed_time":3.583432434,"remaining_time":3.583432434},
{"learn":[0.2767373562],"iteration":50,"passed_time":3.653305508,"remaining_time":3.510038625},
{"learn":[0.274633488],"iteration":51,"passed_time":3.716577103,"remaining_time":3.430686557},
{"learn":[0.2726269109],"iteration":52,"passed_time":3.782725478,"remaining_time":3.354492405},
{"learn":[0.2702521283],"iteration":53,"passed_time":3.861292533,"remaining_time":3.289249195},
{"learn":[0.2686777891],"iteration":54,"passed_time":3.931303289,"remaining_time":3.216520873},
{"learn":[0.2666578729],"iteration":55,"passed_time":3.999546007,"remaining_time":3.142500434},
{"learn":[0.2644016279],"iteration":56,"passed_time":4.06368019,"remaining_time":3.065583301},
{"learn":[0.2627211816],"iteration":57,"passed_time":4.12743881,"remaining_time":2.988835},
{"learn":[0.2607106876],"iteration":58,"passed_time":4.192424108,"remaining_time":2.913379465},
{"learn":[0.259247442],"iteration":59,"passed_time":4.256269511,"remaining_time":2.837513007},
{"learn":[0.2578587505],"iteration":60,"passed_time":4.315113235,"remaining_time":2.758842888},
{"learn":[0.2560198321],"iteration":61,"passed_time":4.382694648,"remaining_time":2.686167688},
{"learn":[0.2544092887],"iteration":62,"passed_time":4.444423402,"remaining_time":2.610216919},
{"learn":[0.2530225059],"iteration":63,"passed_time":4.497988841,"remaining_time":2.530118723},
{"learn":[0.2512770666],"iteration":64,"passed_time":4.560969541,"remaining_time":2.455906676},
{"learn":[0.2497849955],"iteration":65,"passed_time":4.616046035,"remaining_time":2.377963109},
{"learn":[0.2483904062],"iteration":66,"passed_time":4.674637766,"remaining_time":2.302433526},
{"learn":[0.2455489077],"iteration":67,"passed_time":4.740112753,"remaining_time":2.230641295},
{"learn":[0.2437839467],"iteration":68,"passed_time":4.805717375,"remaining_time":2.159090415},
{"learn":[0.2424225126],"iteration":69,"passed_time":4.875456589,"remaining_time":2.089481395},
{"learn":[0.2412577983],"iteration":70,"passed_time":4.934491676,"remaining_time":2.0154966},
{"learn":[0.2398734297],"iteration":71,"passed_time":5.003144531,"remaining_time":1.945667318},
{"learn":[0.2384525272],"iteration":72,"passed_time":5.072181184,"remaining_time":1.876012219},
{"learn":[0.2371550969],"iteration":73,"passed_time":5.145652922,"remaining_time":1.807932108},
{"learn":[0.2361228412],"iteration":74,"passed_time":5.21463253,"remaining_time":1.738210843},
{"learn":[0.2346700668],"iteration":75,"passed_time":5.28532607,"remaining_time":1.669050338},
{"learn":[0.2335604191],"iteration":76,"passed_time":5.360582035,"remaining_time":1.601212816},
{"learn":[0.2323167256],"iteration":77,"passed_time":5.435197687,"remaining_time":1.533004476},
{"learn":[0.2311103167],"iteration":78,"passed_time":5.514165603,"remaining_time":1.465790856},
{"learn":[0.2295343821],"iteration":79,"passed_time":5.583320444,"remaining_time":1.395830111},
{"learn":[0.228220644],"iteration":80,"passed_time":5.660373244,"remaining_time":1.327741872},
{"learn":[0.2278813471],"iteration":81,"passed_time":5.745460655,"remaining_time":1.26119868},
{"learn":[0.2268169458],"iteration":82,"passed_time":5.81473278,"remaining_time":1.190969365},
{"learn":[0.2253817286],"iteration":83,"passed_time":5.881439473,"remaining_time":1.120274185},
{"learn":[0.2243308272],"iteration":84,"passed_time":5.943524352,"remaining_time":1.048857239},
{"learn":[0.2232180636],"iteration":85,"passed_time":6.011714437,"remaining_time":0.9786511875},
{"learn":[0.2221276883],"iteration":86,"passed_time":6.080172582,"remaining_time":0.9085315352},
{"learn":[0.2208370386],"iteration":87,"passed_time":6.14838325,"remaining_time":0.8384158977},
{"learn":[0.2192471709],"iteration":88,"passed_time":6.211687251,"remaining_time":0.7677366265},
{"learn":[0.218475117],"iteration":89,"passed_time":6.275578309,"remaining_time":0.6972864788},
{"learn":[0.2175942326],"iteration":90,"passed_time":6.342156724,"remaining_time":0.6272462694},
{"learn":[0.2167737498],"iteration":91,"passed_time":6.405812463,"remaining_time":0.5570271707},
{"learn":[0.2157098184],"iteration":92,"passed_time":6.478970428,"remaining_time":0.4876644408},
{"learn":[0.2146329171],"iteration":93,"passed_time":6.551617578,"remaining_time":0.4181883561},
{"learn":[0.2138128131],"iteration":94,"passed_time":6.626797886,"remaining_time":0.3487788361},
{"learn":[0.2128805515],"iteration":95,"passed_time":6.705627728,"remaining_time":0.2794011553},
{"learn":[0.2117377227],"iteration":96,"passed_time":6.786113347,"remaining_time":0.2098797942},
{"learn":[0.2107316385],"iteration":97,"passed_time":6.848785143,"remaining_time":0.1397711254},
{"learn":[0.2098503985],"iteration":98,"passed_time":6.919423767,"remaining_time":0.06989316937},
{"learn":[0.2088736275],"iteration":99,"passed_time":6.983211394,"remaining_time":0}
]}